cryptofinance/__init__.py
cryptofinance/utils/__init__.py
cryptofinance/utils/coingecko_resolver.py
cryptofinance/utils/get_history.py
cryptofinance/utils/get_market_cap.py
cryptofinance/utils/get_price.py
cryptofinance/utils/get_volume.py
cryptofinance/utils/plot_price.py
cryptofinance/utils/search_symbol.py
crypto_yfinance-0.1.3.dist-info/METADATA
crypto_yfinance-0.1.3.dist-info/WHEEL
crypto_yfinance-0.1.3.dist-info/top_level.txt
crypto_yfinance-0.1.3.dist-info/RECORD
