Metadata-Version: 2.1
Name: crypto-yfinance
Version: 0.1.3
Summary: Unified cryptocurrency data API like yfinance
Home-page: https://medium.com/@craakash
Author: Aakash Chavan Ravindranath
Author-email: craakash@gmail.com
License: MIT
Project-URL: LinkedIn, https://www.linkedin.com/in/aakashcr/
Project-URL: Source, https://github.com/craakash/cryptofinance
Classifier: Programming Language :: Python :: 3
Classifier: License :: OSI Approved :: MIT License
Classifier: Operating System :: OS Independent
Requires-Python: >=3.8
Requires-Dist: ccxt
Requires-Dist: pycoingecko
Requires-Dist: matplotlib
Requires-Dist: pandas
Requires-Dist: plotly
